counterpropagation/__init__.py
counterpropagation/core/__init__.py
counterpropagation/core/cp.py
counterpropagation/core/initializer.py
counterpropagation/core/response_layer.py
counterpropagation/utils/__init__.py
counterpropagation/utils/callbacks.py
counterpropagation/utils/evalmeasure.py
counterpropagation/utils/visualization.py
counterprop_prototorch-1.0.3.dist-info/LICENSE
counterprop_prototorch-1.0.3.dist-info/METADATA
counterprop_prototorch-1.0.3.dist-info/WHEEL
counterprop_prototorch-1.0.3.dist-info/top_level.txt
counterprop_prototorch-1.0.3.dist-info/RECORD
